brainvision.py
brainvision-0.4.dist-info/LICENSE-BSD.txt
brainvision-0.4.dist-info/LICENSE-GPLv3.txt
brainvision-0.4.dist-info/METADATA
brainvision-0.4.dist-info/WHEEL
brainvision-0.4.dist-info/top_level.txt
brainvision-0.4.dist-info/RECORD
