Metadata-Version: 2.2
Name: brainvision
Version: 0.4
Summary: Read and write EEG data in the BrainVision Core data format
Author: Robert Oostenveld
Author-email: r.oostenveld@donders.ru.nl
Project-URL: homepage, https://github.com/robertoostenveld/brainvision
Project-URL: repository, https://github.com/robertoostenveld/brainvision
Classifier: Programming Language :: Python :: 3.8
Classifier: Operating System :: OS Independent
Classifier: Intended Audience :: Science/Research
Requires-Python: >=3.8
License-File: LICENSE-BSD.txt
License-File: LICENSE-GPLv3.txt
Requires-Dist: numpy
